{
  "items": [
    {
      "id": 1,
      "driver": {
        "name": "Ai Nanfing",
        "phone": "+65 9234 5678"
      },
      "vehicle": {
        "branch": "Lamborghini Aventador C",
        "plate": "SGD1235F"
      }
    },
    {
      "id": 2,
      "driver": {
        "name": "Lee Meng Soon",
        "phone": "+65 9445 7423"
      },
      "vehicle": {
        "branch": "Lamborghini Aventador",
        "plate": "SGD1234F"
      }
    },
    {
      "id": 3,
      "vehicle": {
        "branch": "Lamborghini Aventador L",
        "plate": "LKK1200F"
      }
    },
    {
      "id": 4,
      "driver": {
        "name": "Li Nanxing",
        "phone": "+65 9445 7422"
      },
      "vehicle": {
        "branch": "Lamborghini Aventador C",
        "plate": "SGD1235F"
      }
    },
    {
      "driver": {
        "name": "Lee Yinzhu",
        "phone": "+65 9445 7522"
      }
    },
    {
      "id": 5,
      "driver": {
        "name": "Wee Dinzhu",
        "phone": "+65 1000 7522"
      }
    }
  ]
}
